beansieve/__init__.py
beansieve/__main__.py
beansieve/lib/__init__.py
beansieve/lib/aggregate.py
beansieve/lib/archive.py
beansieve/lib/commands.py
beansieve/lib/fs.py
beansieve/lib/structure.py
beansieve/lib/beanfile/Balance.py
beansieve/lib/beanfile/Close.py
beansieve/lib/beanfile/Commodity.py
beansieve/lib/beanfile/Custom.py
beansieve/lib/beanfile/Document.py
beansieve/lib/beanfile/Event.py
beansieve/lib/beanfile/Note.py
beansieve/lib/beanfile/Open.py
beansieve/lib/beanfile/Option.py
beansieve/lib/beanfile/Pad.py
beansieve/lib/beanfile/Price.py
beansieve/lib/beanfile/Query.py
beansieve/lib/beanfile/Reader.py
beansieve/lib/beanfile/Transaction.py
beansieve/lib/beanfile/Writer.py
beansieve/lib/beanfile/__init__.py
beansieve/lib/entry/Entry.py
beansieve/lib/entry/__init__.py
beansieve/lib/predicate/__init__.py
beansieve/lib/predicate/account.py
beansieve/lib/predicate/date.py
beansieve/lib/predicate/type.py
beansieve-0.1.1.dist-info/LICENSE
beansieve-0.1.1.dist-info/METADATA
beansieve-0.1.1.dist-info/WHEEL
beansieve-0.1.1.dist-info/top_level.txt
beansieve-0.1.1.dist-info/RECORD
