Metadata-Version: 2.1
Name: beansieve
Version: 0.1.1
Summary: A small tools for arrange beancount files
Author-email: ezirmusitua <jferroal@gmail.com>
Project-URL: Homepage, https://github.com/ezirmusitua/beansieve
Project-URL: Bug Tracker, https://github.com/ezirmusitua/beansieve/issues
Classifier: Programming Language :: Python :: 3
Classifier: License :: OSI Approved :: MIT License
Classifier: Operating System :: OS Independent
Requires-Python: >=3.7
License-File: LICENSE
Requires-Dist: beancount ==2.3.5
